src/vm.v
module vending_machine (
    input [1:0] coin, 
    input clk, reset, 
    output dispense 
);

    reg [1:0] PS;// Present State
    wire [1:0] NS;// Next State

    always @(posedge clk or posedge reset) begin
        if(reset) PS <= 2'd0;
        else PS <= NS;
    end

    
    assign NS[0] = (~PS[1] & ~PS[0] & coin[0]) | (PS[0] & ~coin[1] & ~coin[0]);
    assign NS[1] = (~PS[1] & ~PS[0] & coin[1]) | (PS[0] & coin[0]) | (PS[1] & ~coin[1] & ~coin[0]);
    assign dispense = (coin[1] & ~coin[0] & (PS[0] | PS[1])) | (~coin[1] & coin[0] & PS[1]);

endmodule

tb/tb_vm.v
module tb_vending_machine;
    reg clk, rst;
    reg [1:0] coin_in;
    wire disp;

    vending_machine uut (
        .clk(clk),
        .reset(rst),
        .coin(coin_in),
        .dispense(disp)
    );

    always #5 clk = ~clk;

    initial begin
        $dumpfile("tb.vm.vcd");
        $dumpvars(0, tb_vending_machine);
        clk = 0;
        rst = 1;
        coin_in = 2'b00;
        
        $monitor("T=%0t | rst=%b | coin=%b | disp=%b", $time, rst, coin_in, disp);

        @(negedge clk) rst = 0;

        // 5 + 5 + 5
        @(negedge clk) coin_in = 2'b01;
        @(negedge clk) coin_in = 2'b01;
        @(negedge clk) coin_in = 2'b01;
        @(negedge clk) coin_in = 2'b00;

        // 5 + 10
        @(negedge clk) coin_in = 2'b01;
        @(negedge clk) coin_in = 2'b10;
        @(negedge clk) coin_in = 2'b00;

        // 10 + 5
        @(negedge clk) coin_in = 2'b10;
        @(negedge clk) coin_in = 2'b01;
        @(negedge clk) coin_in = 2'b00;

        // 10 + 10 overflow
        @(negedge clk) coin_in = 2'b10;
        @(negedge clk) coin_in = 2'b10;
        @(negedge clk) coin_in = 2'b00;

        // reset check mid-transaction
        @(negedge clk) coin_in = 2'b01;
        @(negedge clk) coin_in = 2'b01;
        @(negedge clk) rst = 1;      
        @(negedge clk) rst = 0;      
        coin_in = 2'b00;

        // invalid coin check
        @(negedge clk) coin_in = 2'b01; 
        @(negedge clk) coin_in = 2'b11; 

        #20 $finish;
    end
endmodule

tb.vm.vcd
$date
	Tue Jun 16 18:50:18 2026
$end
$version
	Icarus Verilog
$end
$timescale
	1s
$end
$scope module tb_vending_machine $end
$var wire 1 ! disp $end
$var reg 1 " clk $end
$var reg 2 # coin_in [1:0] $end
$var reg 1 $ rst $end
$scope module uut $end
$var wire 1 " clk $end
$var wire 2 % coin [1:0] $end
$var wire 1 ! dispense $end
$var wire 1 $ reset $end
$var wire 2 & NS [1:0] $end
$var reg 2 ' PS [1:0] $end
$upscope $end
$upscope $end
$enddefinitions $end
#0
$dumpvars
b0 '
b0 &
b0 %
1$
b0 #
0"
0!
$end
#5
1"
#10
0$
0"
#15
1"
#20
b1 &
b1 #
b1 %
0"
#25
b10 &
b1 '
1"
#30
0"
#35
b0 &
1!
b10 '
1"
#40
0"
#45
b1 &
0!
b0 '
1"
#50
b0 &
b0 #
b0 %
0"
#55
1"
#60
b1 &
b1 #
b1 %
0"
#65
b10 &
b1 '
1"
#70
b0 &
1!
b10 #
b10 %
0"
#75
b10 &
0!
b0 '
1"
#80
b0 &
b0 #
b0 %
0"
#85
1"
#90
b10 &
b10 #
b10 %
0"
#95
b0 &
1!
b10 '
1"
#100
b1 #
b1 %
0"
#105
b1 &
0!
b0 '
1"
#110
b0 &
b0 #
b0 %
0"
#115
1"
#120
b10 &
b10 #
b10 %
0"
#125
b0 &
1!
b10 '
1"
#130
0"
#135
b10 &
0!
b0 '
1"
#140
b0 &
b0 #
b0 %
0"
#145
1"
#150
b1 &
b1 #
b1 %
0"
#155
b10 &
b1 '
1"
#160
0"
#165
b0 &
1!
b10 '
1"
#170
b1 &
0!
b0 '
1$
0"
#175
1"
#180
b0 &
b0 #
b0 %
0$
0"
#185
1"
#190
b1 &
b1 #
b1 %
0"
#195
b10 &
b1 '
1"
#200
b11 #
b11 %
0"
#205
b0 &
b10 '
1"
#210
0"
#215
b11 &
b0 '
1"
